pycarlo/__init__.py
pycarlo/common/__init__.py
pycarlo/common/errors.py
pycarlo/common/files.py
pycarlo/common/http.py
pycarlo/common/mcon.py
pycarlo/common/retries.py
pycarlo/common/settings.py
pycarlo/common/utils.py
pycarlo/core/__init__.py
pycarlo/core/client.py
pycarlo/core/endpoint.py
pycarlo/core/operations.py
pycarlo/core/session.py
pycarlo/features/__init__.py
pycarlo/features/exceptions.py
pycarlo/features/agent/__init__.py
pycarlo/features/agent/models.py
pycarlo/features/agent/queries.py
pycarlo/features/agent/service.py
pycarlo/features/circuit_breakers/__init__.py
pycarlo/features/circuit_breakers/exceptions.py
pycarlo/features/circuit_breakers/service.py
pycarlo/features/dbt/__init__.py
pycarlo/features/dbt/dbt_importer.py
pycarlo/features/dbt/queries.py
pycarlo/features/metadata/__init__.py
pycarlo/features/metadata/asset_allow_block_list.py
pycarlo/features/metadata/asset_filters_container.py
pycarlo/features/metadata/base_allow_block_list.py
pycarlo/features/metadata/metadata_allow_block_list.py
pycarlo/features/metadata/metadata_filters_container.py
pycarlo/features/pii/__init__.py
pycarlo/features/pii/constants.py
pycarlo/features/pii/pii_filterer.py
pycarlo/features/pii/queries.py
pycarlo/features/pii/service.py
pycarlo/features/user/__init__.py
pycarlo/features/user/exceptions.py
pycarlo/features/user/models.py
pycarlo/features/user/queries.py
pycarlo/features/user/service.py
pycarlo/lib/README.md
pycarlo/lib/__init__.py
pycarlo/lib/schema.json
pycarlo/lib/schema.py
pycarlo/lib/types.py
pycarlo-0.12.108.dist-info/LICENSE
pycarlo-0.12.108.dist-info/METADATA
pycarlo-0.12.108.dist-info/WHEEL
pycarlo-0.12.108.dist-info/top_level.txt
pycarlo-0.12.108.dist-info/RECORD
