Metadata-Version: 2.1
Name: pycarlo
Version: 0.12.108
Summary: Monte Carlo's Python SDK
Home-page: https://www.montecarlodata.com/
Author: Monte Carlo Data, Inc
Author-email: info@montecarlodata.com
License: Apache Software License (Apache 2.0)
Classifier: Development Status :: 3 - Alpha
Classifier: Intended Audience :: Developers
Classifier: Natural Language :: English
Classifier: Topic :: Software Development :: Build Tools
Classifier: License :: OSI Approved :: Apache Software License
Classifier: Programming Language :: Python :: 3.8
Classifier: Programming Language :: Python :: 3.9
Classifier: Programming Language :: Python :: 3.10
Classifier: Programming Language :: Python :: 3.11
Classifier: Programming Language :: Python :: 3.12
Requires-Python: >=3.8
License-File: LICENSE
Requires-Dist: dataclasses-json<6.0.0,>=0.5.7
Requires-Dist: python-box>=5.0.0
Requires-Dist: requests<3.0.0,>=2.0.0
Requires-Dist: responses>=0.20.0
Requires-Dist: sgqlc<17.0,>=14.1
